{
  "generado_en": "2026-06-07T14:55:46.111559+00:00",
  "estado_general": "NO LISTO",
  "conteo_estados": {
    "COMPLETO": 9,
    "PARCIAL": 3,
    "FALTA": 1
  },
  "completos": [
    "D1 SQL relacional",
    "D1 carga real y validación post-carga",
    "D2 NoSQL documental",
    "D3 integración y trazabilidad",
    "D4 Change Data Capture",
    "D5 Testing y validación",
    "D5 consultas y dashboard coherente",
    "D7 Streamlit",
    "D8 Docker/despliegue"
  ],
  "parciales": [
    "D3 ETL Python modular",
    "D3 idempotencia",
    "D9 rendimiento"
  ],
  "faltantes": [
    "D6 Seguridad y gobernanza"
  ],
  "no_verificados": [],
  "urgente_alta": [
    {
      "Criterio": "D3 ETL Python modular",
      "Estado": "PARCIAL",
      "Evidencia encontrada": "extractores=True; config_externa=True; secretos=6; logs_d3=0; ultima_exit_ok=False",
      "Riesgo": "Secretos o falta de evidencia de ejecución afectan entrega.",
      "Urgencia": "ALTA",
      "Acción recomendada": "Ejecutar D3 evidencia con PYTHONPATH correcto y guardar logs.",
      "¿Se puede terminar hoy?": "SI"
    }
  ],
  "urgencias": [
    {
      "Criterio": "D3 ETL Python modular",
      "Estado": "PARCIAL",
      "Evidencia encontrada": "extractores=True; config_externa=True; secretos=6; logs_d3=0; ultima_exit_ok=False",
      "Riesgo": "Secretos o falta de evidencia de ejecución afectan entrega.",
      "Urgencia": "ALTA",
      "Acción recomendada": "Ejecutar D3 evidencia con PYTHONPATH correcto y guardar logs.",
      "¿Se puede terminar hoy?": "SI"
    },
    {
      "Criterio": "D3 idempotencia",
      "Estado": "PARCIAL",
      "Evidencia encontrada": "natural/record_hash=13 columnas; duplicados=[{'stg_firms': 0}, {'stg_meteo': 0}, {'stg_chirps': 0}, {'stg_modis': 0}, {'stg_calidad_aire': 0}]; logs_idempotencia=1; dos_corridas=False",
      "Riesgo": "Sin dos corridas consecutivas, idempotencia queda parcialmente demostrada.",
      "Urgencia": "MEDIA",
      "Acción recomendada": "Generar corrida 1 y 2 smoke con conteo antes/después.",
      "¿Se puede terminar hoy?": "SI"
    },
    {
      "Criterio": "D9 rendimiento",
      "Estado": "PARCIAL",
      "Evidencia encontrada": "logs=1; tiempos_consultas=True; tiempos_pipeline=False; indices=False; completa_vs_smoke=False",
      "Riesgo": "Sin tiempos cuantitativos, el rendimiento queda como afirmación cualitativa.",
      "Urgencia": "MEDIA",
      "Acción recomendada": "Guardar tabla de tiempos de vistas/pipeline y explicar impacto de índices y smoke vs carga completa.",
      "¿Se puede terminar hoy?": "SI"
    }
  ],
  "se_puede_terminar_hoy": true,
  "condiciones_para_terminar_hoy": [
    "Ejecutar D3 evidencia con PYTHONPATH correcto y guardar logs.",
    "Generar corrida 1 y 2 smoke con conteo antes/después.",
    "Guardar tabla de tiempos de vistas/pipeline y explicar impacto de índices y smoke vs carga completa."
  ]
}